TwistedWebsocket
