Metadata-Version: 1.1
Name: TwistedWebsocket
Version: 0.0.7
Summary: Websocket server implementation based on Twisted with SSL support.
Home-page: https://github.com/tuxlinuxien/TwistedWebsocket
Author: Yoann Cerda
Author-email: tuxlinuxien@gmail.com
License: MIT
Keywords: websocket server twisted ssl
Platform: UNKNOWN
Classifier: Development Status :: 2 - Pre-Alpha
Classifier: Environment :: Console
Classifier: Framework :: Twisted
Classifier: Intended Audience :: Developers
